odoo/addons/printing_auto_mrp/README.rst
odoo/addons/printing_auto_mrp/__init__.py
odoo/addons/printing_auto_mrp/__manifest__.py
odoo/addons/printing_auto_mrp/i18n/it.po
odoo/addons/printing_auto_mrp/i18n/printing_auto_mrp.pot
odoo/addons/printing_auto_mrp/models/__init__.py
odoo/addons/printing_auto_mrp/models/mrp_production.py
odoo/addons/printing_auto_mrp/readme/CONFIGURE.md
odoo/addons/printing_auto_mrp/readme/CONTRIBUTORS.md
odoo/addons/printing_auto_mrp/readme/DESCRIPTION.md
odoo/addons/printing_auto_mrp/static/description/icon.png
odoo/addons/printing_auto_mrp/static/description/index.html
odoo/addons/printing_auto_mrp/tests/__init__.py
odoo/addons/printing_auto_mrp/tests/test_printing_auto_mrp_production.py
odoo/addons/printing_auto_mrp/views/mrp_production.xml
odoo_addon_printing_auto_mrp-18.0.1.0.0.5.dist-info/METADATA
odoo_addon_printing_auto_mrp-18.0.1.0.0.5.dist-info/WHEEL
odoo_addon_printing_auto_mrp-18.0.1.0.0.5.dist-info/top_level.txt
odoo_addon_printing_auto_mrp-18.0.1.0.0.5.dist-info/RECORD
