Metadata-Version: 2.1
Name: odoo-addon-printing_auto_mrp
Version: 18.0.1.0.0.5
Requires-Python: >=3.10
Requires-Dist: odoo-addon-printing_auto_stock_picking==18.0.*
Requires-Dist: odoo==18.0.*
Summary: Printing Auto MRP
Home-page: https://github.com/OCA/manufacture
License: AGPL-3
Author: Camptocamp, BCIM, Odoo Community Association (OCA)
Author-email: support@odoo-community.org
Classifier: Programming Language :: Python
Classifier: Framework :: Odoo
Classifier: Framework :: Odoo :: 18.0
Classifier: License :: OSI Approved :: GNU Affero General Public License v3
